capturejob/__init__.py
capturejob/__main__.py
capturejob/service/fileservice.py
capturejob-0.3.1.dist-info/entry_points.txt
capturejob-0.3.1.dist-info/WHEEL
capturejob-0.3.1.dist-info/METADATA
capturejob-0.3.1.dist-info/RECORD
