Metadata-Version: 2.1
Name: capturejob
Version: 0.3.1
Summary: A library to capture job outputs to persistent storage
License: MIT
Author: aurecon
Requires-Python: >=3.8,<4.0
Classifier: License :: OSI Approved :: MIT License
Classifier: Programming Language :: Python :: 3
Classifier: Programming Language :: Python :: 3.10
Classifier: Programming Language :: Python :: 3.8
Classifier: Programming Language :: Python :: 3.9
Requires-Dist: azure-storage-blob (>=12.9.0,<13.0.0)
Requires-Dist: dotmap (>=1.3.26,<2.0.0)
Requires-Dist: dyndebug (>=0.2.0,<0.3.0)
Requires-Dist: loguru (>=0.5.3,<0.6.0)
Requires-Dist: python-dotenv (>=0.19.2,<0.20.0)
